drf_pydantic_openapi/__init__.py
drf_pydantic_openapi/apps.py
drf_pydantic_openapi/errors.py
drf_pydantic_openapi/exception_handler.py
drf_pydantic_openapi/generator.py
drf_pydantic_openapi/path.py
drf_pydantic_openapi/ref_source.py
drf_pydantic_openapi/ref_utils.py
drf_pydantic_openapi/settings.py
drf_pydantic_openapi/static/drf_pydantic_openapi/css/swagger-ui.css
drf_pydantic_openapi/static/drf_pydantic_openapi/js/rapidoc-min.js
drf_pydantic_openapi/static/drf_pydantic_openapi/js/redoc.standalone.js
drf_pydantic_openapi/static/drf_pydantic_openapi/js/swagger-ui-bundle.js
drf_pydantic_openapi/templates/drf_pydantic_openapi/rapidoc.html
drf_pydantic_openapi/templates/drf_pydantic_openapi/redoc.html
drf_pydantic_openapi/templates/drf_pydantic_openapi/swagger.html
drf_pydantic_openapi/urls.py
drf_pydantic_openapi/utils.py
drf_pydantic_openapi/views.py
drf_pydantic_openapi-0.6.4.dist-info/LICENSE
drf_pydantic_openapi-0.6.4.dist-info/METADATA
drf_pydantic_openapi-0.6.4.dist-info/WHEEL
drf_pydantic_openapi-0.6.4.dist-info/RECORD
