Metadata-Version: 2.1
Name: drf-pydantic-openapi
Version: 0.6.4
Summary: OpenAPI (v3) schema generation via Pydantic models using Django REST Framework.
Author: iKlotho
Author-email: umutkahrimanedu@gmail.com
Requires-Python: >=3.10,<4.0
Classifier: Programming Language :: Python :: 3
Classifier: Programming Language :: Python :: 3.10
Classifier: Programming Language :: Python :: 3.11
Requires-Dist: django (>=3.2.1)
Requires-Dist: djangorestframework (>=3.13)
Requires-Dist: docstring-parser (>=0.15)
Requires-Dist: jsonref (>=1.1.0,<2.0.0)
Requires-Dist: loguru (>=0.5.3)
Requires-Dist: openapi-pydantic (==0.4.0)
